sshcontroller/__init__.py
sshcontroller/sshcontroller.py
sshcontroller-1.5.dist-info/LICENSE
sshcontroller-1.5.dist-info/METADATA
sshcontroller-1.5.dist-info/WHEEL
sshcontroller-1.5.dist-info/top_level.txt
sshcontroller-1.5.dist-info/RECORD
