Metadata-Version: 2.1
Name: sshcontroller
Version: 1.5
Summary: A package to easily run SSH commands
Home-page: https://github.com/ojroques/python-sshcontroller
Author: Olivier Roques
Author-email: olivier@oroques.dev
License: UNKNOWN
Platform: UNKNOWN
Classifier: Programming Language :: Python :: 3
Classifier: Intended Audience :: Developers
Classifier: License :: OSI Approved :: GNU Lesser General Public License v2 or later (LGPLv2+)
Classifier: Operating System :: OS Independent
Classifier: Topic :: Internet
Classifier: Topic :: Security :: Cryptography
Classifier: Topic :: Software Development
Requires-Python: >=3.6
Requires-Dist: paramiko
